geodummy/__init__.py
geodummy/helloworld.py
geodummy-0.0.3.dist-info/LICENSE
geodummy-0.0.3.dist-info/METADATA
geodummy-0.0.3.dist-info/WHEEL
geodummy-0.0.3.dist-info/entry_points.txt
geodummy-0.0.3.dist-info/top_level.txt
geodummy-0.0.3.dist-info/RECORD
