Metadata-Version: 2.1
Name: geodummy
Version: 0.0.3
Summary: A handy geospatial tool package for processing geospatial data
Home-page: UNKNOWN
Author: Weixing Zhang
Author-email: weixing.zhang365@gmail.com
License: UNKNOWN
Keywords: python,geospatial,gis,remote sensing
Platform: UNKNOWN
Classifier: Development Status :: 1 - Planning
Classifier: Intended Audience :: Developers
Classifier: Programming Language :: Python :: 3
Classifier: Operating System :: Unix
Classifier: Operating System :: MacOS :: MacOS X
Classifier: Operating System :: Microsoft :: Windows
Requires-Dist: numpy
